agsem_data_crawler/__init__.py
agsem_data_crawler/main.py
agsem_data_crawler-0.1.0.dist-info/METADATA
agsem_data_crawler-0.1.0.dist-info/WHEEL
agsem_data_crawler-0.1.0.dist-info/RECORD
